{
  "releases": [
    {
      "version": "2.1.584",
      "notes": "Release 2.1.584 (stable channel)",
      "channel": "stable",
      "date": "2026-04-12T15:28:22.226Z",
      "files": [
        {
          "name": "Redball-2.1.584-Setup.exe",
          "size": 68819694,
          "hash": "0efbf3b4b451973022aa4a36ce5883ec669027d0c2a04406aa9352e9e6d58269",
          "downloads": 0,
          "uploadedAt": "2026-04-12T15:28:22.497Z"
        },
        {
          "name": "Redball-2.1.584.zip",
          "size": 10709978,
          "hash": "e3ccb3d14a262ebc404bf495da38e92c9c433864f47af4d1b4f50b224f5b8a4c",
          "downloads": 0,
          "uploadedAt": "2026-04-12T15:28:22.524Z"
        },
        {
          "name": "Redball.Core.dll.patch",
          "size": 79206,
          "hash": "ce1e253b49df281c75eb17031df407f05edb197d338f7e77783ad70c82250987",
          "downloads": 0,
          "uploadedAt": "2026-04-12T15:28:27.779Z",
          "patchFor": "binaries/Redball.Core.dll",
          "originalSize": 201728,
          "savings": 122522
        },
        {
          "name": "Redball.Service.exe.patch",
          "size": 781194,
          "hash": "7d3fd30f1ecfbf5b95ffdd1d42828ecb7b26806ca837c507031e22a0473a45b3",
          "downloads": 0,
          "uploadedAt": "2026-04-12T15:28:27.781Z",
          "patchFor": "binaries/Redball.Service.exe",
          "originalSize": 2203727,
          "savings": 1422533
        },
        {
          "name": "Redball.UI.WPF.dll.patch",
          "size": 1214094,
          "hash": "ab4fed5cdf6ef2ede1ddb45bd957d3ad27635cc0cfa501c5a30190d3248872cb",
          "downloads": 0,
          "uploadedAt": "2026-04-12T15:28:27.784Z",
          "patchFor": "binaries/Redball.UI.WPF.dll",
          "originalSize": 2839040,
          "savings": 1624946
        },
        {
          "name": "Redball.UI.WPF.exe.patch",
          "size": 375,
          "hash": "1cc030f48abc855c4b67aab439a4960ba0adcfa67247a87c352d5901c8bd66a1",
          "downloads": 0,
          "uploadedAt": "2026-04-12T15:28:27.785Z",
          "patchFor": "binaries/Redball.UI.WPF.exe",
          "originalSize": 373760,
          "savings": 373385
        },
        {
          "name": "patch-manifest.json.patch",
          "size": 430,
          "hash": "29ea22de0dc3b48e97af31f0834eeb53af98bcd2845507a7ba4abf66c211ac3b",
          "downloads": 0,
          "uploadedAt": "2026-04-12T15:28:27.785Z",
          "patchFor": "patches/patch-manifest.json",
          "originalSize": 1343,
          "savings": 913
        }
      ],
      "totalDownloads": 0,
      "patchInfo": {
        "fromVersion": "2.1.583",
        "generatedAt": "2026-04-12T15:28:27.775Z",
        "totalPatches": 5,
        "totalSavings": 3544299
      }
    },
    {
      "version": "2.1.585",
      "notes": "Release 2.1.585 (stable channel)",
      "channel": "stable",
      "date": "2026-04-12T15:32:48.846Z",
      "files": [
        {
          "name": "Redball-2.1.585-Setup.exe",
          "size": 68818080,
          "hash": "a514b90d75c9f4e8760243670964a5b65917c7bd6a12c69d5c9bdbccb687f35f",
          "downloads": 0,
          "uploadedAt": "2026-04-12T15:32:49.019Z"
        },
        {
          "name": "Redball-2.1.585.zip",
          "size": 10710220,
          "hash": "4db8415e14b966e8e739859d3f8a0ce2352f2b08c478ac652445ab1e7374bc68",
          "downloads": 0,
          "uploadedAt": "2026-04-12T15:32:49.041Z"
        },
        {
          "name": "Redball.Core.dll.patch",
          "size": 79212,
          "hash": "8b68bd283ab35859c8922cd11fa1da62f05ecba45fc6c3334779aee6683ce523",
          "downloads": 0,
          "uploadedAt": "2026-04-12T15:32:54.518Z",
          "patchFor": "binaries/Redball.Core.dll",
          "originalSize": 201728,
          "savings": 122516
        },
        {
          "name": "Redball.Service.exe.patch",
          "size": 781194,
          "hash": "9fae8607bedcd177bdf8324f59a47c480033c324dfcda313f25e9e8ec3fff252",
          "downloads": 0,
          "uploadedAt": "2026-04-12T15:32:54.520Z",
          "patchFor": "binaries/Redball.Service.exe",
          "originalSize": 2203727,
          "savings": 1422533
        },
        {
          "name": "Redball.UI.WPF.dll.patch",
          "size": 1214105,
          "hash": "263109c9f23cfc789154dc4d8ef13792c28ecce09083790d248895a43762e608",
          "downloads": 0,
          "uploadedAt": "2026-04-12T15:32:54.523Z",
          "patchFor": "binaries/Redball.UI.WPF.dll",
          "originalSize": 2840064,
          "savings": 1625959
        },
        {
          "name": "Redball.UI.WPF.exe.patch",
          "size": 377,
          "hash": "d9a5cd09b2cdee5cd18d9d12bca3ffc417b7b1e77aef525a1b214050f6b1721a",
          "downloads": 0,
          "uploadedAt": "2026-04-12T15:32:54.524Z",
          "patchFor": "binaries/Redball.UI.WPF.exe",
          "originalSize": 373760,
          "savings": 373383
        },
        {
          "name": "patch-manifest.json.patch",
          "size": 432,
          "hash": "49a6ab1cf0b5c89d3ad9aaad7c12828116e6fdbb61993fa252528b517783239c",
          "downloads": 0,
          "uploadedAt": "2026-04-12T15:32:54.524Z",
          "patchFor": "patches/patch-manifest.json",
          "originalSize": 1343,
          "savings": 911
        }
      ],
      "totalDownloads": 0,
      "patchInfo": {
        "fromVersion": "2.1.584",
        "generatedAt": "2026-04-12T15:32:54.511Z",
        "totalPatches": 5,
        "totalSavings": 3545302
      }
    },
    {
      "version": "2.1.586",
      "notes": "Release 2.1.586 (stable channel)",
      "channel": "stable",
      "date": "2026-04-12T15:51:08.971Z",
      "files": [
        {
          "name": "Redball-2.1.586-Setup.exe",
          "size": 68818053,
          "hash": "d858c56872b0ef1a562a22de3e31399a25cdc34bcbca6db8c57436ce85a78d26",
          "downloads": 0,
          "uploadedAt": "2026-04-12T15:51:09.181Z"
        },
        {
          "name": "Redball-2.1.586.zip",
          "size": 10710433,
          "hash": "ceb53233c65fd5612d9884226dfd31c6a522d457bc88acd96354ea5da520aaef",
          "downloads": 0,
          "uploadedAt": "2026-04-12T15:51:09.209Z"
        },
        {
          "name": "Redball.Core.dll.patch",
          "size": 79208,
          "hash": "e4b8782542658959b0a3656f1ebce1734680b760f4bf6dff2702d39caa88c0ba",
          "downloads": 0,
          "uploadedAt": "2026-04-12T15:51:14.417Z",
          "patchFor": "binaries/Redball.Core.dll",
          "originalSize": 201728,
          "savings": 122520
        },
        {
          "name": "Redball.Service.exe.patch",
          "size": 781198,
          "hash": "d5e46f167d7512978100c2f00fffea2e2b155e523d2a54980d092fd2ae18f72b",
          "downloads": 0,
          "uploadedAt": "2026-04-12T15:51:14.419Z",
          "patchFor": "binaries/Redball.Service.exe",
          "originalSize": 2203727,
          "savings": 1422529
        },
        {
          "name": "Redball.UI.WPF.dll.patch",
          "size": 1214275,
          "hash": "d7dffe69c671efd8bf8889de1b59c24c53b18f0aa15d4e7f2a5a092f3c2c71a1",
          "downloads": 0,
          "uploadedAt": "2026-04-12T15:51:14.422Z",
          "patchFor": "binaries/Redball.UI.WPF.dll",
          "originalSize": 2840064,
          "savings": 1625789
        },
        {
          "name": "Redball.UI.WPF.exe.patch",
          "size": 377,
          "hash": "2cd7107b7c38ce3fa67ffbaca2afd099a1caa96a20331efb19af5d056e99958e",
          "downloads": 0,
          "uploadedAt": "2026-04-12T15:51:14.423Z",
          "patchFor": "binaries/Redball.UI.WPF.exe",
          "originalSize": 373760,
          "savings": 373383
        },
        {
          "name": "patch-manifest.json.patch",
          "size": 429,
          "hash": "00a111643586fdbd91bde681a3a139edf92e0217e11d088013c255516bb2b454",
          "downloads": 0,
          "uploadedAt": "2026-04-12T15:51:14.423Z",
          "patchFor": "patches/patch-manifest.json",
          "originalSize": 1343,
          "savings": 914
        }
      ],
      "totalDownloads": 0,
      "patchInfo": {
        "fromVersion": "2.1.585",
        "generatedAt": "2026-04-12T15:51:14.414Z",
        "totalPatches": 5,
        "totalSavings": 3545135
      }
    },
    {
      "version": "2.1.587",
      "notes": "Release 2.1.587 (stable channel)",
      "channel": "stable",
      "date": "2026-04-12T15:59:06.123Z",
      "files": [
        {
          "name": "Redball-2.1.587-Setup.exe",
          "size": 68818266,
          "hash": "a944e0200a3ec39265dbc90552ab1e2250e300166db65e0b44da4f37ee3edc49",
          "downloads": 0,
          "uploadedAt": "2026-04-12T15:59:06.361Z"
        },
        {
          "name": "Redball-2.1.587.zip",
          "size": 10710282,
          "hash": "4735db6b2fbf06e68179f7c13f4c5c048db8d256233997b2e443dc9e526c0e92",
          "downloads": 0,
          "uploadedAt": "2026-04-12T15:59:06.409Z"
        },
        {
          "name": "Redball.Core.dll.patch",
          "size": 79209,
          "hash": "edc1d62614989e83efba41cdf133a3d3eba4669ee676b7929033bc3d1f7abe40",
          "downloads": 0,
          "uploadedAt": "2026-04-12T15:59:12.689Z",
          "patchFor": "binaries/Redball.Core.dll",
          "originalSize": 201728,
          "savings": 122519
        },
        {
          "name": "Redball.Service.exe.patch",
          "size": 781181,
          "hash": "28b626eaf2592e1da954bdd571c74df3cda3ef7fc15207ca9163b84fe479272e",
          "downloads": 0,
          "uploadedAt": "2026-04-12T15:59:12.693Z",
          "patchFor": "binaries/Redball.Service.exe",
          "originalSize": 2203727,
          "savings": 1422546
        },
        {
          "name": "Redball.UI.WPF.dll.patch",
          "size": 1214110,
          "hash": "98e1b5c1127cce4a255befb9d5d2b04542b168e3fa57d4475c9abcfb752f480a",
          "downloads": 0,
          "uploadedAt": "2026-04-12T15:59:12.698Z",
          "patchFor": "binaries/Redball.UI.WPF.dll",
          "originalSize": 2840064,
          "savings": 1625954
        },
        {
          "name": "Redball.UI.WPF.exe.patch",
          "size": 377,
          "hash": "094976187825ecd72cf0afbaaa939a98be40410d27ed5982276482e16421a007",
          "downloads": 0,
          "uploadedAt": "2026-04-12T15:59:12.699Z",
          "patchFor": "binaries/Redball.UI.WPF.exe",
          "originalSize": 373760,
          "savings": 373383
        },
        {
          "name": "patch-manifest.json.patch",
          "size": 432,
          "hash": "040917d899d02800cd7c00e4791c937d7e6cce5aaa999ea4041c11512644acbb",
          "downloads": 0,
          "uploadedAt": "2026-04-12T15:59:12.699Z",
          "patchFor": "patches/patch-manifest.json",
          "originalSize": 1343,
          "savings": 911
        }
      ],
      "totalDownloads": 0,
      "patchInfo": {
        "fromVersion": "2.1.586",
        "generatedAt": "2026-04-12T15:59:12.685Z",
        "totalPatches": 5,
        "totalSavings": 3545313
      }
    },
    {
      "version": "2.1.590",
      "notes": "Release 2.1.590 (stable channel)",
      "channel": "stable",
      "date": "2026-04-12T16:36:49.590Z",
      "files": [
        {
          "name": "Redball-2.1.590-Setup.exe",
          "size": 68817310,
          "hash": "1825706e16bc0de38b863ffe12300527bada8ca28dfa2e84f3f5965aaf5e5cc0",
          "downloads": 0,
          "uploadedAt": "2026-04-12T16:36:49.821Z"
        },
        {
          "name": "Redball-2.1.590.zip",
          "size": 10709983,
          "hash": "9449f44dc984b13f8eddd005e8fe460145c86f5307a7440ccac302c792447e12",
          "downloads": 0,
          "uploadedAt": "2026-04-12T16:36:49.861Z"
        },
        {
          "name": "Redball.Core.dll.patch",
          "size": 79215,
          "hash": "31c1109e0665d92bac4b7c98705c1c318d435ab7d7c5a43317fc6e1e2f53707b",
          "downloads": 0,
          "uploadedAt": "2026-04-12T16:36:55.407Z",
          "patchFor": "binaries/Redball.Core.dll",
          "originalSize": 201728,
          "savings": 122513
        },
        {
          "name": "Redball.Service.exe.patch",
          "size": 781197,
          "hash": "43ed1606ed71ebf4ae58a2f072eed6a0ffeb58be97c7091401e97bbdbfee9574",
          "downloads": 0,
          "uploadedAt": "2026-04-12T16:36:55.456Z",
          "patchFor": "binaries/Redball.Service.exe",
          "originalSize": 2203727,
          "savings": 1422530
        },
        {
          "name": "Redball.UI.WPF.dll.patch",
          "size": 1213874,
          "hash": "fe7e7bcdeddda34baac9313ece01b84041b4ed62a998d521316e389dc7b63ae5",
          "downloads": 0,
          "uploadedAt": "2026-04-12T16:36:55.463Z",
          "patchFor": "binaries/Redball.UI.WPF.dll",
          "originalSize": 2840064,
          "savings": 1626190
        },
        {
          "name": "Redball.UI.WPF.exe.patch",
          "size": 376,
          "hash": "86c9aeff174c58415b076fe735c4f136b0a1e517078cf3ef79f4c831e989c00b",
          "downloads": 0,
          "uploadedAt": "2026-04-12T16:36:55.473Z",
          "patchFor": "binaries/Redball.UI.WPF.exe",
          "originalSize": 373760,
          "savings": 373384
        },
        {
          "name": "patch-manifest.json.patch",
          "size": 427,
          "hash": "0129c3461678ad5dc904cf219713f414319523a249090cbc7461447be5076822",
          "downloads": 0,
          "uploadedAt": "2026-04-12T16:36:55.474Z",
          "patchFor": "patches/patch-manifest.json",
          "originalSize": 1343,
          "savings": 916
        }
      ],
      "totalDownloads": 0,
      "patchInfo": {
        "fromVersion": "2.1.587",
        "generatedAt": "2026-04-12T16:36:55.404Z",
        "totalPatches": 5,
        "totalSavings": 3545533
      }
    },
    {
      "version": "2.1.591",
      "notes": "Release 2.1.591 (stable channel)",
      "channel": "stable",
      "date": "2026-04-12T16:48:46.707Z",
      "files": [
        {
          "name": "Redball-2.1.591-Setup.exe",
          "size": 68818041,
          "hash": "ddc9b2c05a90f7474cdbb38b354e9d0e686f4f6a4f61d37a45c19243d2fc51b2",
          "downloads": 0,
          "uploadedAt": "2026-04-12T16:48:46.952Z"
        },
        {
          "name": "Redball-2.1.591.zip",
          "size": 10710306,
          "hash": "eaabcd8098d27beca86ddcfee69b9ab298b2856e4e4cc7a652ce87cb454eacc0",
          "downloads": 0,
          "uploadedAt": "2026-04-12T16:48:46.988Z"
        },
        {
          "name": "Redball.Core.dll.patch",
          "size": 79205,
          "hash": "93e49910b2df29578a1f1d5afdc8b9c41087d7d0ac0555f4ab182be2ca6e0e15",
          "downloads": 0,
          "uploadedAt": "2026-04-12T16:48:52.113Z",
          "patchFor": "binaries/Redball.Core.dll",
          "originalSize": 201728,
          "savings": 122523
        },
        {
          "name": "Redball.Service.exe.patch",
          "size": 781184,
          "hash": "07b5c86a2fe23e81fc1171f8152072b5cd50bff473a002b08456fd11be86ea9b",
          "downloads": 0,
          "uploadedAt": "2026-04-12T16:48:52.115Z",
          "patchFor": "binaries/Redball.Service.exe",
          "originalSize": 2203727,
          "savings": 1422543
        },
        {
          "name": "Redball.UI.WPF.dll.patch",
          "size": 1214222,
          "hash": "63e009ea77131868152e95ea9c020fb9b53e017019d506049151e90d2bc1a193",
          "downloads": 0,
          "uploadedAt": "2026-04-12T16:48:52.119Z",
          "patchFor": "binaries/Redball.UI.WPF.dll",
          "originalSize": 2840064,
          "savings": 1625842
        },
        {
          "name": "Redball.UI.WPF.exe.patch",
          "size": 374,
          "hash": "03f0b6d7746a17323acb8be5ba1331025cb5836403400528167a9bc80028f602",
          "downloads": 0,
          "uploadedAt": "2026-04-12T16:48:52.120Z",
          "patchFor": "binaries/Redball.UI.WPF.exe",
          "originalSize": 373760,
          "savings": 373386
        },
        {
          "name": "patch-manifest.json.patch",
          "size": 432,
          "hash": "e1e4dec484969c81c3af4b959654397cb749e068badc7fcb02e5914610d6dffa",
          "downloads": 0,
          "uploadedAt": "2026-04-12T16:48:52.120Z",
          "patchFor": "patches/patch-manifest.json",
          "originalSize": 1343,
          "savings": 911
        }
      ],
      "totalDownloads": 0,
      "patchInfo": {
        "fromVersion": "2.1.590",
        "generatedAt": "2026-04-12T16:48:52.107Z",
        "totalPatches": 5,
        "totalSavings": 3545205
      }
    }
  ]
}