{
  "fromVersion": "2.1.481",
  "toVersion": "2.1.483",
  "generatedAt": "2026-04-09T07:24:09.589Z",
  "patches": [
    {
      "file": "binaries/Redball.Service.dll",
      "patchFile": "Redball.Service.dll.patch",
      "patchSize": 118618,
      "originalSize": 240128,
      "savings": 121510,
      "savingsPercent": "50.6%"
    },
    {
      "file": "binaries/Redball.Service.exe",
      "patchFile": "Redball.Service.exe.patch",
      "patchSize": 379,
      "originalSize": 373760,
      "savings": 373381,
      "savingsPercent": "99.9%"
    },
    {
      "file": "binaries/Redball.UI.WPF.dll",
      "patchFile": "Redball.UI.WPF.dll.patch",
      "patchSize": 1199083,
      "originalSize": 2806784,
      "savings": 1607701,
      "savingsPercent": "57.3%"
    },
    {
      "file": "binaries/Redball.UI.WPF.exe",
      "patchFile": "Redball.UI.WPF.exe.patch",
      "patchSize": 377,
      "originalSize": 373760,
      "savings": 373383,
      "savingsPercent": "99.9%"
    },
    {
      "file": "patches/patch-manifest.json",
      "patchFile": "patch-manifest.json.patch",
      "patchSize": 411,
      "originalSize": 1344,
      "savings": 933,
      "savingsPercent": "69.4%"
    }
  ],
  "skipped": [
    {
      "file": "Redball-2.1.483-Setup.exe",
      "reason": "not_worthwhile",
      "savings": "1.1%"
    },
    {
      "file": "Redball-2.1.483.exe",
      "reason": "new_file"
    },
    {
      "file": "Redball-2.1.483.zip",
      "reason": "new_file"
    },
    {
      "file": "patches/Redball.Service.dll.patch",
      "reason": "not_worthwhile",
      "savings": "-0.0%"
    },
    {
      "file": "patches/Redball.Service.exe.patch",
      "reason": "too_small"
    },
    {
      "file": "patches/Redball.UI.WPF.dll.patch",
      "reason": "not_worthwhile",
      "savings": "0.5%"
    },
    {
      "file": "patches/Redball.UI.WPF.exe.patch",
      "reason": "too_small"
    }
  ],
  "totalSavings": 2476908,
  "totalOriginalSize": 84149512
}